loginpy/__init__.py
loginpy-0.0.2.dist-info/LICENSE
loginpy-0.0.2.dist-info/METADATA
loginpy-0.0.2.dist-info/WHEEL
loginpy-0.0.2.dist-info/top_level.txt
loginpy-0.0.2.dist-info/RECORD
