Metadata-Version: 2.1
Name: loginpy
Version: 0.0.2
Summary: A simple Flask library to make login management easier.
Home-page: https://gitea.com/chopin42/login.py
Author: SnowCode
License: UNKNOWN
Platform: UNKNOWN
Classifier: Programming Language :: Python :: 3
Classifier: License :: OSI Approved :: MIT License
Classifier: Operating System :: OS Independent
Requires-Python: >=3.6
